uipath_scaffold_generator/SequencesToScaffold.xlsx
uipath_scaffold_generator/__init__.py
uipath_scaffold_generator/functions.py
uipath_scaffold_generator/generator.py
uipath_scaffold_generator/project.py
uipath_scaffold_generator/sequence.py
uipath_scaffold_generator-0.0.3.dist-info/LICENSE
uipath_scaffold_generator-0.0.3.dist-info/METADATA
uipath_scaffold_generator-0.0.3.dist-info/WHEEL
uipath_scaffold_generator-0.0.3.dist-info/top_level.txt
uipath_scaffold_generator-0.0.3.dist-info/RECORD
