Metadata-Version: 2.1
Name: uipath-scaffold-generator
Version: 0.0.3
Summary: Generator system that provides scaffolding for your UiPath projects/sequences.
Home-page: https://github.com/christianblandford/UiPath-Scaffold-Generator
Author: Christian Blandford
Author-email: christianblandford@me.com
License: UNKNOWN
Platform: UNKNOWN
Classifier: Programming Language :: Python :: 3
Classifier: License :: OSI Approved :: MIT License
Classifier: Operating System :: OS Independent
Requires-Dist: beautifulsoup4 (>=4.7.1)
Requires-Dist: uipath (>=0.0.1)
Requires-Dist: openpyxl (>=2.6.1)
